LICENSE.txt
MANIFEST.in
README.rst
pyproject.toml
setup.cfg
setup.py
installer/cppyy_monkey_patch.py
installer/__pycache__/cppyy_monkey_patch.cpython-310.pyc
installer/__pycache__/cppyy_monkey_patch.cpython-311.pyc
installer/__pycache__/cppyy_monkey_patch.cpython-312.pyc
installer/__pycache__/cppyy_monkey_patch.cpython-313.pyc
installer/__pycache__/cppyy_monkey_patch.cpython-38.pyc
python/cppyy/__init__.py
python/cppyy/_cpython_cppyy.py
python/cppyy/_pypy_cppyy.py
python/cppyy/_pythonization.py
python/cppyy/_stdcpp_fix.py
python/cppyy/_typemap.py
python/cppyy/_version.py
python/cppyy/interactive.py
python/cppyy/ll.py
python/cppyy/numba_ext.py
python/cppyy/reflex.py
python/cppyy/types.py
python/cppyy.egg-info/PKG-INFO
python/cppyy.egg-info/SOURCES.txt
python/cppyy.egg-info/dependency_links.txt
python/cppyy.egg-info/entry_points.txt
python/cppyy.egg-info/not-zip-safe
python/cppyy.egg-info/requires.txt
python/cppyy.egg-info/top_level.txt
python/cppyy/__pyinstaller/__init__.py
python/cppyy/__pyinstaller/hook-cppyy.py