Metadata-Version: 2.1
Name: cppyy
Version: 3.5.0
Summary: Cling-based Python-C++ bindings
Home-page: http://cppyy.readthedocs.org
Author: Wim Lavrijsen
Author-email: WLavrijsen@lbl.gov
License: LBNL BSD
Keywords: C++ bindings data science calling language integration
Classifier: Development Status :: 5 - Production/Stable
Classifier: Intended Audience :: Developers
Classifier: Topic :: Software Development
Classifier: Topic :: Software Development :: Interpreters
Classifier: License :: OSI Approved :: BSD License
Classifier: Programming Language :: Python :: Implementation :: PyPy
Classifier: Programming Language :: Python :: 3
Classifier: Programming Language :: Python :: 3.6
Classifier: Programming Language :: Python :: 3.7
Classifier: Programming Language :: Python :: 3.8
Classifier: Programming Language :: Python :: 3.9
Classifier: Programming Language :: Python :: 3.10
Classifier: Programming Language :: C
Classifier: Programming Language :: C++
Classifier: Natural Language :: English
License-File: LICENSE.txt
